drummer/__init__.py
drummer/configuration.py
drummer/drummer.py
drummer/drummered.py
drummer/errors.py
drummer/logger.py
drummer/messages.py
drummer/commands/__init__.py
drummer/commands/base.py
drummer/commands/env.py
drummer/commands/imex.py
drummer/commands/jobs.py
drummer/commands/service.py
drummer/commands/tasks/__init__.py
drummer/commands/tasks/taskexec.py
drummer/commands/tasks/tasklist.py
drummer/commands/tasks/taskupdate.py
drummer/database/__init__.py
drummer/database/schedule.py
drummer/database/sessions.py
drummer/database/sqlbase.py
drummer/events/__init__.py
drummer/events/jobs.py
drummer/events/sockets.py
drummer/jobs/__init__.py
drummer/jobs/job.py
drummer/jobs/loader.py
drummer/jobs/manager.py
drummer/local/__init__.py
drummer/local/data.py
drummer/sockets/__init__.py
drummer/sockets/client.py
drummer/sockets/commonsocket.py
drummer/sockets/server.py
drummer/tasks/__init__.py
drummer/tasks/managed.py
drummer/tasks/manager.py
drummer/tasks/task.py
drummer/utils/__init__.py
drummer/utils/fio.py
drummer/utils/queued.py
drummer/utils/validation.py
drummer/workers/__init__.py
drummer/workers/extender.py
drummer/workers/listener.py
drummer/workers/runner.py
drummer/workers/scheduler.py
drummer-1.3.1.data/scripts/drummer-admin
drummer-1.3.1.dist-info/LICENSE
drummer-1.3.1.dist-info/METADATA
drummer-1.3.1.dist-info/WHEEL
drummer-1.3.1.dist-info/top_level.txt
drummer-1.3.1.dist-info/RECORD
