Metadata-Version: 2.1
Name: drummer
Version: 1.3.1
Summary: A multi-process, multi-tasking job scheduler.
Home-page: https://github.com/acapitanelli/drummer
Author: Andrea Capitanelli
Author-email: andrea.capitanelli@gmail.com
Maintainer: Andrea Capitanelli
Maintainer-email: andrea.capitanelli@gmail.com
License: MIT
Keywords: scheduler extender multi-process multi-tasking
Platform: UNKNOWN
Classifier: Development Status :: 4 - Beta
Classifier: License :: OSI Approved :: MIT License
Classifier: Operating System :: POSIX :: Linux
Classifier: Programming Language :: Python :: 3
Classifier: Topic :: System
Requires-Python: >=3.6.0
Requires-Dist: PTable
Requires-Dist: PyYAML
Requires-Dist: SQLAlchemy
Requires-Dist: clips
Requires-Dist: croniter
Requires-Dist: inquirer
